[
  {
    "id": 1,
    "word": "subsequent",
    "meaning": "【形】その次の、そのあとの",
    "example": "The subsequent chapters explain the theory in detail.",
    "translation": "その次の章では理論が詳しく説明されています。",
    "remark": ""
  },
  {
    "id": 2,
    "word": "thoughtfully",
    "meaning": "【副】深く考えて、思慮深く、配慮して",
    "example": "She nodded thoughtfully before giving her answer.",
    "translation": "彼女は答える前に思慮深くうなずいた。",
    "remark": ""
  },
  {
    "id": 3,
    "word": "abridged",
    "meaning": "【形】要約された、短縮された",
    "example": "This is an abridged version of the original novel.",
    "translation": "これは原作の要約版です。",
    "remark": ""
  },
  {
    "id": 4,
    "word": "carpool",
    "meaning": "【動】相乗りする　【名】相乗り",
    "example": "We decided to carpool to work to save money.",
    "translation": "節約のために私たちは相乗りして通勤することにしました。",
    "remark": ""
  },
  {
    "id": 5,
    "word": "compatible",
    "meaning": "【形】相性が良い、互換性がある、共存できる",
    "example": "This software is compatible with both Windows and Mac.",
    "translation": "このソフトはWindowsとMacの両方に互換性があります。",
    "remark": ""
  },
  {
    "id": 6,
    "word": "endorse",
    "meaning": "【動】推薦する、指示する、裏書きする",
    "example": "Many celebrities endorse this product.",
    "translation": "多くの有名人がこの製品を推薦しています。",
    "remark": ""
  },
  {
    "id": 7,
    "word": "explicit",
    "meaning": "【形】明白な、明確な",
    "example": "The instructions were explicit and easy to follow.",
    "translation": "説明は明確で、わかりやすかったです。",
    "remark": ""
  },
  {
    "id": 8,
    "word": "keenly",
    "meaning": "【副】痛烈に、鋭く",
    "example": "He was keenly aware of the risks involved.",
    "translation": "彼はそのリスクを痛烈に認識していました。",
    "remark": ""
  },
  {
    "id": 9,
    "word": "plaque",
    "meaning": "【名】縦",
    "example": "A memorial plaque was placed on the wall.",
    "translation": "記念の銘板が壁に設置されました。",
    "remark": ""
  },
  {
    "id": 10,
    "word": "dilute",
    "meaning": "【動】薄める",
    "example": "Please dilute the juice with water before drinking.",
    "translation": "ジュースは飲む前に水で薄めてください。",
    "remark": ""
  },
  {
    "id": 11,
    "word": "exempt",
    "meaning": "【形】免除された　【動】免除する",
    "example": "Students are exempt from the tax.",
    "translation": "学生はその税金を免除されています。",
    "remark": ""
  },
  {
    "id": 12,
    "word": "centerpiece",
    "meaning": "【名】中心に置かれる装飾品、中心になるもの",
    "example": "The vase was the centerpiece of the dining table.",
    "translation": "その花瓶が食卓の中心の装飾でした。",
    "remark": ""
  },
  {
    "id": 13,
    "word": "oversight",
    "meaning": "【名】見落とし、手落ち、監視",
    "example": "The error was due to an unfortunate oversight.",
    "translation": "そのミスは不幸な見落としが原因でした。",
    "remark": ""
  },
  {
    "id": 14,
    "word": "privileged",
    "meaning": "【形】光栄な",
    "example": "I'm privileged to be part of this project.",
    "translation": "このプロジェクトに参加できて光栄です。",
    "remark": ""
  },
  {
    "id": 15,
    "word": "recur",
    "meaning": "【動】再発する",
    "example": "The same problem may recur if not addressed properly.",
    "translation": "きちんと対処しなければ同じ問題が再発するかもしれません。",
    "remark": ""
  },
  {
    "id": 16,
    "word": "skeptical",
    "meaning": "【形】懐疑的な、疑い深い",
    "example": "She was skeptical of his explanation.",
    "translation": "彼女は彼の説明に懐疑的でした。",
    "remark": ""
  },
  {
    "id": 17,
    "word": "sustainable",
    "meaning": "【形】持続可能な",
    "example": "We aim to build a sustainable energy system.",
    "translation": "私たちは持続可能なエネルギーシステムを構築することを目指しています。",
    "remark": ""
  },
  {
    "id": 18,
    "word": "artifact",
    "meaning": "【名】(歴史的・文化的価値のある)工芸品、手工品",
    "example": "The museum displays ancient artifacts.",
    "translation": "その博物館では古代の工芸品が展示されています。",
    "remark": ""
  },
  {
    "id": 19,
    "word": "keynote",
    "meaning": "【形】基調となる　【名】基調",
    "example": "The keynote speaker inspired the whole audience.",
    "translation": "基調講演者は聴衆全体に感動を与えました。",
    "remark": ""
  },
  {
    "id": 20,
    "word": "breathtaking",
    "meaning": "【形】息をのむほどの、驚くべき",
    "example": "The view from the mountain was breathtaking.",
    "translation": "山からの景色は息をのむほど美しかったです。",
    "remark": ""
  },
  {
    "id": 21,
    "word": "cubicle",
    "meaning": "【名】個別の作業スペース",
    "example": "I work in a small office cubicle.",
    "translation": "私は小さなオフィスの作業スペースで働いています。",
    "remark": ""
  },
  {
    "id": 22,
    "word": "outage",
    "meaning": "【名】機能停止期間、供給停止期間",
    "example": "The power outage lasted for three hours.",
    "translation": "停電は3時間続きました。",
    "remark": ""
  },
  {
    "id": 23,
    "word": "perishable",
    "meaning": "【形】傷みやすい、腐りやすい",
    "example": "Store perishable items in the refrigerator.",
    "translation": "傷みやすい食品は冷蔵庫に保管してください。",
    "remark": ""
  },
  {
    "id": 24,
    "word": "avid",
    "meaning": "【形】熱心な、熱烈な",
    "example": "He is an avid reader of science fiction.",
    "translation": "彼はSF小説の熱心な読者です。",
    "remark": ""
  },
  {
    "id": 25,
    "word": "detour",
    "meaning": "【名】回り道　【動】遠回りをする",
    "example": "We had to take a detour due to road construction.",
    "translation": "道路工事のため回り道をしなければなりませんでした。",
    "remark": ""
  },
  {
    "id": 26,
    "word": "expedite",
    "meaning": "【動】早める、促進させる",
    "example": "We need to expedite the delivery process.",
    "translation": "配送プロセスを早める必要があります。",
    "remark": ""
  },
  {
    "id": 27,
    "word": "vicinity",
    "meaning": "【名】近所、近辺",
    "example": "There are many shops in the vicinity of the station.",
    "translation": "駅の近辺には多くの店があります。",
    "remark": ""
  },
  {
    "id": 28,
    "word": "affiliated",
    "meaning": "【形】提携した、関連のある",
    "example": "He is affiliated with a major university.",
    "translation": "彼は大手大学と提携しています。",
    "remark": ""
  },
  {
    "id": 29,
    "word": "definitive",
    "meaning": "【形】決定版の、最終的な",
    "example": "This is the definitive guide to wine tasting.",
    "translation": "これはワインテイスティングの決定版ガイドです。",
    "remark": ""
  },
  {
    "id": 30,
    "word": "demolish",
    "meaning": "【動】(建物を)解体する、取り壊す",
    "example": "They plan to demolish the old building next week.",
    "translation": "来週その古い建物を解体する予定です。",
    "remark": ""
  },
  {
    "id": 31,
    "word": "feasible",
    "meaning": "【形】実現可能な",
    "example": "It is a feasible solution to the problem.",
    "translation": "それは問題に対する実現可能な解決策です。",
    "remark": ""
  },
  {
    "id": 32,
    "word": "inaugural",
    "meaning": "【形】最初の、初開催の",
    "example": "He attended the inaugural ceremony.",
    "translation": "彼は初開催の式典に出席しました。",
    "remark": ""
  },
  {
    "id": 33,
    "word": "installment",
    "meaning": "【名】分割払いの1回分",
    "example": "The first installment is due next month.",
    "translation": "分割払いの1回目は来月が期日です。",
    "remark": ""
  },
  {
    "id": 34,
    "word": "redeemable",
    "meaning": "【形】(現金や商品と)交換可能な",
    "example": "This coupon is redeemable for cash.",
    "translation": "このクーポンは現金と交換可能です。",
    "remark": ""
  },
  {
    "id": 35,
    "word": "streamline",
    "meaning": "【動】合理化する、簡略化する",
    "example": "We need to streamline our workflow.",
    "translation": "業務の流れを合理化する必要があります。",
    "remark": ""
  },
  {
    "id": 36,
    "word": "insulation",
    "meaning": "【名】(音、熱、電気等を)防ぐこと",
    "example": "Proper insulation helps reduce energy costs.",
    "translation": "適切な断熱はエネルギーコスト削減に役立ちます。",
    "remark": ""
  },
  {
    "id": 37,
    "word": "intact",
    "meaning": "【形】傷がない",
    "example": "The package arrived intact.",
    "translation": "荷物は無傷で届きました。",
    "remark": ""
  },
  {
    "id": 38,
    "word": "occupancy",
    "meaning": "【名】(ホテルや部屋等の)占有、占有人数",
    "example": "Hotel occupancy dropped during the off-season.",
    "translation": "閑散期にはホテルの占有率が下がりました。",
    "remark": ""
  },
  {
    "id": 39,
    "word": "turnover",
    "meaning": "【名】離職率",
    "example": "The company is struggling with high employee turnover.",
    "translation": "その会社は高い離職率に悩んでいます。",
    "remark": ""
  },
  {
    "id": 40,
    "word": "unanimous",
    "meaning": "【形】満場一致の",
    "example": "The decision was unanimous.",
    "translation": "その決定は満場一致でした。",
    "remark": ""
  },
  {
    "id": 41,
    "word": "deteriorate",
    "meaning": "【動】悪化する",
    "example": "The patient's condition began to deteriorate.",
    "translation": "患者の容態は悪化し始めました。",
    "remark": ""
  },
  {
    "id": 42,
    "word": "sturdy",
    "meaning": "【形】頑丈な、丈夫な",
    "example": "This is a sturdy piece of furniture.",
    "translation": "これは頑丈な家具です。",
    "remark": ""
  },
  {
    "id": 43,
    "word": "adverse",
    "meaning": "【形】よくない、不利な",
    "example": "He suffered from adverse side effects.",
    "translation": "彼は好ましくない副作用に悩まされました。",
    "remark": ""
  },
  {
    "id": 44,
    "word": "bearer",
    "meaning": "【名】(小切手やクーポン等の)持参人",
    "example": "The bearer of this check can cash it at any bank.",
    "translation": "この小切手の持参人はどの銀行でも現金化できます。",
    "remark": ""
  },
  {
    "id": 45,
    "word": "unprecedented",
    "meaning": "【形】前例のない",
    "example": "The event drew an unprecedented crowd.",
    "translation": "そのイベントには前例のない数の人が集まりました。",
    "remark": ""
  },
  {
    "id": 46,
    "word": "botanical",
    "meaning": "【形】植物の、植物学の",
    "example": "They visited a botanical garden.",
    "translation": "彼らは植物園を訪れました。",
    "remark": ""
  },
  {
    "id": 47,
    "word": "commensurate",
    "meaning": "【形】つりあった、比例した、見合った",
    "example": "Salary will be commensurate with experience.",
    "translation": "給料は経験に見合ったものになります。",
    "remark": ""
  },
  {
    "id": 48,
    "word": "consecutive",
    "meaning": "【形】連続した",
    "example": "He won three consecutive games.",
    "translation": "彼は3試合連続で勝ちました。",
    "remark": ""
  },
  {
    "id": 49,
    "word": "deliberation",
    "meaning": "【名】熟考",
    "example": "The decision was made after much deliberation.",
    "translation": "熟考の末にその決定が下されました。",
    "remark": ""
  },
  {
    "id": 50,
    "word": "discreetly",
    "meaning": "【副】分別をもって、思慮深く",
    "example": "She discreetly left the meeting.",
    "translation": "彼女は分別を持って会議を退席しました。",
    "remark": ""
  },
  {
    "id": 51,
    "word": "entail",
    "meaning": "【動】必要とする、～を伴う",
    "example": "This job entails a lot of responsibility.",
    "translation": "この仕事は多くの責任を伴います。",
    "remark": ""
  },
  {
    "id": 52,
    "word": "fluctuation",
    "meaning": "【名】変動",
    "example": "There has been a fluctuation in stock prices.",
    "translation": "株価に変動がありました。",
    "remark": ""
  },
  {
    "id": 53,
    "word": "foremost",
    "meaning": "【形】最高の、トップの",
    "example": "She is the foremost expert in the field.",
    "translation": "彼女はその分野で最高の専門家です。",
    "remark": ""
  },
  {
    "id": 54,
    "word": "imperative",
    "meaning": "【形】急を要する、非常に重要な",
    "example": "It is imperative that we act now.",
    "translation": "今すぐ行動することが非常に重要です。",
    "remark": ""
  },
  {
    "id": 55,
    "word": "mandatory",
    "meaning": "【形】義務の、強制の",
    "example": "Wearing a helmet is mandatory.",
    "translation": "ヘルメットの着用は義務です。",
    "remark": ""
  },
  {
    "id": 56,
    "word": "meticulously",
    "meaning": "【副】最新の注意を払って、几帳面に",
    "example": "He prepared the report meticulously.",
    "translation": "彼はその報告書を几帳面に準備しました。",
    "remark": ""
  },
  {
    "id": 57,
    "word": "outreach",
    "meaning": "【名】福祉活動、支援活動",
    "example": "The organization offers community outreach programs.",
    "translation": "その団体は地域支援活動を提供しています。",
    "remark": ""
  },
  {
    "id": 58,
    "word": "tenure",
    "meaning": "【名】在職期間",
    "example": "He received tenure after ten years of teaching.",
    "translation": "彼は10年の教職の後、終身在職権を得ました。",
    "remark": ""
  },
  {
    "id": 59,
    "word": "versatile",
    "meaning": "【形】多才な",
    "example": "She is a versatile performer.",
    "translation": "彼女は多才なパフォーマーです。",
    "remark": ""
  },
  {
    "id": 60,
    "word": "alleviate",
    "meaning": "【動】和らげる、軽減する",
    "example": "The medicine helped alleviate the pain.",
    "translation": "その薬は痛みを和らげるのに役立ちました。",
    "remark": ""
  },
  {
    "id": 61,
    "word": "exemplary",
    "meaning": "【形】模範的な",
    "example": "She received an award for her exemplary service.",
    "translation": "彼女は模範的なサービスに対して賞を受けました。",
    "remark": ""
  },
  {
    "id": 62,
    "word": "gala",
    "meaning": "【名】祝祭、祭り",
    "example": "They attended a charity gala.",
    "translation": "彼らはチャリティーの祝祭に参加しました。",
    "remark": ""
  },
  {
    "id": 63,
    "word": "mural",
    "meaning": "【名】壁画",
    "example": "The mural on the wall was beautifully painted.",
    "translation": "壁画は美しく描かれていました。",
    "remark": ""
  },
  {
    "id": 64,
    "word": "proprietor",
    "meaning": "【名】オー内、所有者",
    "example": "The proprietor of the shop was very kind.",
    "translation": "その店の所有者はとても親切でした。",
    "remark": ""
  },
  {
    "id": 65,
    "word": "stagnant",
    "meaning": "【形】停滞した",
    "example": "The economy remained stagnant for years.",
    "translation": "経済は何年も停滞したままでした。",
    "remark": ""
  },
  {
    "id": 66,
    "word": "stringent",
    "meaning": "【形】非常に厳しい",
    "example": "The company has implemented stringent safety rules.",
    "translation": "会社は非常に厳しい安全規則を導入しました。",
    "remark": ""
  },
  {
    "id": 67,
    "word": "testimonial",
    "meaning": "【名】推薦文、推薦の声",
    "example": "The website includes customer testimonials.",
    "translation": "そのウェブサイトには顧客の推薦の声が掲載されています。",
    "remark": ""
  },
  {
    "id": 68,
    "word": "turnout",
    "meaning": "【名】参加者数、来場者数",
    "example": "The event had a large turnout.",
    "translation": "そのイベントには多くの来場者がありました。",
    "remark": ""
  },
  {
    "id": 69,
    "word": "waive",
    "meaning": "【動】(権利や条件を)放棄する、差し控える、適用しない",
    "example": "They decided to waive the admission fee.",
    "translation": "彼らは入場料を放棄することに決めました。",
    "remark": ""
  },
  {
    "id": 70,
    "word": "faucet",
    "meaning": "【名】蛇口",
    "example": "Please turn off the faucet after use.",
    "translation": "使用後は蛇口を閉めてください。",
    "remark": ""
  },
  {
    "id": 71,
    "word": "amendment",
    "meaning": "【名】改正、修正",
    "example": "The amendment was approved by the committee.",
    "translation": "その改正は委員会によって承認されました。",
    "remark": ""
  },
  {
    "id": 72,
    "word": "anonymous",
    "meaning": "【形】匿名の",
    "example": "The donor chose to remain anonymous.",
    "translation": "その寄付者は匿名を選びました。",
    "remark": ""
  },
  {
    "id": 73,
    "word": "fraud",
    "meaning": "【名】詐欺",
    "example": "He was arrested for tax fraud.",
    "translation": "彼は税金詐欺で逮捕されました。",
    "remark": ""
  },
  {
    "id": 74,
    "word": "liable",
    "meaning": "【形】法的責任がある",
    "example": "The company is liable for damages.",
    "translation": "その会社は損害に対して法的責任があります。",
    "remark": ""
  },
  {
    "id": 75,
    "word": "considerate",
    "meaning": "【形】思いやりのある、配慮して",
    "example": "She is always considerate of others.",
    "translation": "彼女は常に他人に思いやりを持っています。",
    "remark": ""
  },
  {
    "id": 76,
    "word": "consolidate",
    "meaning": "【動】統合する",
    "example": "We plan to consolidate our offices into one location.",
    "translation": "私たちはオフィスを一か所に統合する予定です。",
    "remark": ""
  },
  {
    "id": 77,
    "word": "vigorous",
    "meaning": "【形】活気のある、精力的な",
    "example": "He made a vigorous effort to solve the problem.",
    "translation": "彼は問題解決に精力的に取り組みました。",
    "remark": ""
  },
  {
    "id": 78,
    "word": "retreat",
    "meaning": "【名】研修旅行、退避、静養",
    "example": "We went on a company retreat in the mountains.",
    "translation": "私たちは山での会社の研修旅行に行きました。",
    "remark": ""
  },
  {
    "id": 79,
    "word": "custodian",
    "meaning": "【名】管理人、守衛",
    "example": "The custodian keeps the building clean.",
    "translation": "管理人が建物を清潔に保っています。",
    "remark": ""
  },
  {
    "id": 80,
    "word": "forge",
    "meaning": "【動】築く、構築する",
    "example": "They forged a strong business relationship.",
    "translation": "彼らは強固なビジネス関係を築きました。",
    "remark": ""
  },
  {
    "id": 81,
    "word": "impending",
    "meaning": "【形】間近に迫った、差し迫った",
    "example": "She is nervous about the impending exam.",
    "translation": "彼女は差し迫った試験に緊張しています。",
    "remark": ""
  },
  {
    "id": 82,
    "word": "itemize",
    "meaning": "【動】項目別にする",
    "example": "Please itemize all your expenses.",
    "translation": "すべての経費を項目別にしてください。",
    "remark": ""
  },
  {
    "id": 83,
    "word": "liaison",
    "meaning": "【名】連絡係、連絡",
    "example": "She acts as a liaison between departments.",
    "translation": "彼女は部署間の連絡係を務めています。",
    "remark": ""
  },
  {
    "id": 84,
    "word": "objectionable",
    "meaning": "【形】深いな、気に障る",
    "example": "His remarks were highly objectionable.",
    "translation": "彼の発言は非常に不快でした。",
    "remark": ""
  },
  {
    "id": 85,
    "word": "repave",
    "meaning": "【動】再舗装する",
    "example": "The city plans to repave the main road.",
    "translation": "市は幹線道路を再舗装する予定です。",
    "remark": ""
  },
  {
    "id": 86,
    "word": "shortcoming",
    "meaning": "【名】欠点、短所",
    "example": "Everyone has some shortcomings.",
    "translation": "誰にでも短所はあります。",
    "remark": ""
  },
  {
    "id": 87,
    "word": "viable",
    "meaning": "【形】実行可能な",
    "example": "This is a viable business model.",
    "translation": "これは実行可能なビジネスモデルです。",
    "remark": ""
  },
  {
    "id": 88,
    "word": "memorabilia",
    "meaning": "【名】記念品",
    "example": "He collects sports memorabilia.",
    "translation": "彼はスポーツの記念品を集めています。",
    "remark": ""
  },
  {
    "id": 89,
    "word": "deplete",
    "meaning": "【動】使い果たす、激減させる",
    "example": "Overfishing has depleted the fish population.",
    "translation": "乱獲により魚の数が激減しました。",
    "remark": ""
  },
  {
    "id": 90,
    "word": "jeopardy",
    "meaning": "【名】危機、危険",
    "example": "His actions put the project in jeopardy.",
    "translation": "彼の行動はプロジェクトを危機に陥れました。",
    "remark": ""
  },
  {
    "id": 91,
    "word": "nominal",
    "meaning": "【形】ほんの僅かの",
    "example": "He receives a nominal fee for his services.",
    "translation": "彼は名ばかりの報酬を受け取っています。",
    "remark": ""
  },
  {
    "id": 92,
    "word": "deviate",
    "meaning": "【動】それる",
    "example": "Do not deviate from the plan.",
    "translation": "計画から逸れないでください。",
    "remark": ""
  },
  {
    "id": 93,
    "word": "forfeit",
    "meaning": "【動】没収される、剥奪される　【名】罰金、犠牲",
    "example": "He had to forfeit the match due to injury.",
    "translation": "彼は怪我のため試合を棄権せざるを得ませんでした。",
    "remark": ""
  },
  {
    "id": 94,
    "word": "bolster",
    "meaning": "【動】強化する、補強する、鼓舞する",
    "example": "Her speech bolstered our confidence.",
    "translation": "彼女のスピーチは私たちの自信を強めました。",
    "remark": ""
  },
  {
    "id": 95,
    "word": "optimal",
    "meaning": "【形】ベストの、最適な",
    "example": "This is the optimal solution to the issue.",
    "translation": "これはその問題に対する最適な解決策です。",
    "remark": ""
  },
  {
    "id": 96,
    "word": "purveyor",
    "meaning": "【名】供給業者、販売業者",
    "example": "They are a purveyor of organic produce.",
    "translation": "彼らは有機農産物の供給業者です。",
    "remark": ""
  },
  {
    "id": 97,
    "word": "raffle",
    "meaning": "【名】福引",
    "example": "I won a prize in the charity raffle.",
    "translation": "チャリティーの福引で賞品が当たりました。",
    "remark": ""
  },
  {
    "id": 98,
    "word": "ventilation",
    "meaning": "【名】歓喜、風通し",
    "example": "Proper ventilation is essential in this room.",
    "translation": "この部屋には適切な換気が不可欠です。",
    "remark": ""
  },
  {
    "id": 99,
    "word": "unwavering",
    "meaning": "【形】揺るがぬ、断固とした",
    "example": "She showed unwavering support for the cause.",
    "translation": "彼女はその目的に揺るがぬ支援を示しました。",
    "remark": ""
  },
  {
    "id": 100,
    "word": "exponentially",
    "meaning": "【副】加速度的に、指数関数的に",
    "example": "The number of users has grown exponentially.",
    "translation": "ユーザー数は加速度的に増えています。",
    "remark": ""
  }
]
